CHANGELOG.txt
LICENSE
MANIFEST.in
README.md
pyproject.toml
setup.cfg
setup.py
tox.ini
src/dogpile_backend_redis_advanced/__init__.py
src/dogpile_backend_redis_advanced/py.typed
src/dogpile_backend_redis_advanced.egg-info/PKG-INFO
src/dogpile_backend_redis_advanced.egg-info/SOURCES.txt
src/dogpile_backend_redis_advanced.egg-info/dependency_links.txt
src/dogpile_backend_redis_advanced.egg-info/not-zip-safe
src/dogpile_backend_redis_advanced.egg-info/requires.txt
src/dogpile_backend_redis_advanced.egg-info/top_level.txt
src/dogpile_backend_redis_advanced/cache/__init__.py
src/dogpile_backend_redis_advanced/cache/serializers.py
src/dogpile_backend_redis_advanced/cache/backends/__init__.py
src/dogpile_backend_redis_advanced/cache/backends/redis_advanced.py
tests/__init__.py
tests/cache/__init__.py
tests/cache/test_custom_serializers.py
tests/cache/test_redis_backend.py
tests/cache/test_redis_serialization.py