Metadata-Version: 2.1
Name: dogpile-backend-redis-advanced
Version: 0.5.0
Summary: Advanced Redis plugins for `dogpile.cache`.
Home-page: https://github.com/jvanasco/dogpile_backend_redis_advanced
Author: Jonathan Vanasco
Author-email: jonathan@findmeon.com
License: BSD
Keywords: caching dogpile
Platform: UNKNOWN
Classifier: Development Status :: 5 - Production/Stable
Classifier: Intended Audience :: Developers
Classifier: Programming Language :: Python
Classifier: Programming Language :: Python :: 3
Requires-Python: >=3.10
Provides-Extra: testing
